citionline/__init__.py
citionline/authors.py
citionline/scraper.py
citionline/utils.py
ghanaiantimes/__init__.py
ghanaiantimes/scraper.py
ghanaiantimes/utils.py
ghanaweb/__init__.py
ghanaweb/scraper.py
ghanaweb/utils.py
graphiconline/__init__.py
graphiconline/scraper.py
graphiconline/utils.py
modernghana/__init__.py
modernghana/demo.py
modernghana/scraper.py
modernghana/utils.py
myjoyonline/__init__.py
myjoyonline/scraper.py
myjoyonline/scrapy.py
myjoyonline/utils.py
mynewsgh/__init__.py
mynewsgh/scraper.py
mynewsgh/utils.py
pulsegh/__init__.py
pulsegh/scraper.py
pulsegh/utils.py
threenews/__init__.py
threenews/scraper.py
threenews/scrapy.py
threenews/utils.py
yen/__init__.py
yen/scraper.py
yen/scrapy.py
yen/utils.py
ghananews_scraper-1.0.28.dist-info/METADATA
ghananews_scraper-1.0.28.dist-info/WHEEL
ghananews_scraper-1.0.28.dist-info/top_level.txt
ghananews_scraper-1.0.28.dist-info/RECORD
