Metadata-Version: 2.1
Name: ghananews-scraper
Version: 1.0.28
Summary: A python package to scrape data from Ghana News Portals
Home-page: https://github.com/donwany/ghananews-scraper
Author: Theophilus Siameh
Author-email: theodondre@gmail.com
License: MIT License
Keywords: Scraper,Data,GhanaNews,GhanaWeb,JoyNews,MyJoyOnline,News,Yen,MyNewsGh,ThreeNews,Web Scraper,Ghana Scraper
Platform: any
Classifier: Development Status :: 5 - Production/Stable
Classifier: Environment :: Console
Classifier: Intended Audience :: Developers
Classifier: Programming Language :: Python
Classifier: Programming Language :: Python :: 3
Classifier: Programming Language :: Python :: 3 :: Only
Classifier: Programming Language :: Python :: 3.7
Classifier: Programming Language :: Python :: 3.8
Classifier: Programming Language :: Python :: 3.9
Classifier: Programming Language :: Python :: 3.10
Classifier: Programming Language :: Python :: 3.11
Classifier: Programming Language :: Python :: Implementation :: CPython
Classifier: Programming Language :: Python :: Implementation :: PyPy
Classifier: Topic :: Software Development :: Libraries :: Python Modules
Classifier: Topic :: Software Development :: Testing
Classifier: Topic :: Utilities
Requires-Python: >=3.7
Requires-Dist: bs4
Requires-Dist: requests
Requires-Dist: loguru
Requires-Dist: selenium ==4.10.0
